DESCRIPTION.rst
MANIFEST.in
README.md
setup.cfg
setup.py
wireframe2html/wireframe2html.py
wireframe2html/wireframe2html.pyc
wireframe2html.egg-info/PKG-INFO
wireframe2html.egg-info/SOURCES.txt
wireframe2html.egg-info/dependency_links.txt
wireframe2html.egg-info/requires.txt
wireframe2html.egg-info/top_level.txt
wireframe2html/examples/Homepage.screen
wireframe2html/examples/Projects_list.screen
wireframe2html/templates/humans.txt
wireframe2html/templates/index.html
wireframe2html/templates/page.tpl
wireframe2html/templates/robots.txt
wireframe2html/templates/assets/Foundation/Buttons.screen/AlertButton.tpl
wireframe2html/templates/assets/Foundation/Buttons.screen/AlertButtonLarge.tpl
wireframe2html/templates/assets/Foundation/Buttons.screen/AlertButtonSmall.tpl
wireframe2html/templates/assets/Foundation/Buttons.screen/AlertButtonTiny.tpl
wireframe2html/templates/assets/Foundation/Buttons.screen/Button.tpl
wireframe2html/templates/assets/Foundation/Buttons.screen/ButtonGroup.tpl
wireframe2html/templates/assets/Foundation/Buttons.screen/ButtonGroupLarge.tpl
wireframe2html/templates/assets/Foundation/Buttons.screen/ButtonGroupSmall.tpl
wireframe2html/templates/assets/Foundation/Callouts_Prompts.screen/AlertStandard.tpl
wireframe2html/templates/assets/Foundation/Content.screen/Table.tpl
wireframe2html/templates/assets/Foundation/Navigation.screen/TopBar.tpl
wireframe2html/templates/assets/Foundation/Typography.screen/Paragraph.tpl
wireframe2html/templates/assets/Foundation/Typography.screen/h1.Header.tpl
wireframe2html/templates/css/foundation.css
wireframe2html/templates/css/foundation.min.css
wireframe2html/templates/css/normalize.css
wireframe2html/templates/img/.gitkeep
wireframe2html/templates/js/foundation.min.js
wireframe2html/templates/js/foundation/foundation.abide.js
wireframe2html/templates/js/foundation/foundation.accordion.js
wireframe2html/templates/js/foundation/foundation.alert.js
wireframe2html/templates/js/foundation/foundation.clearing.js
wireframe2html/templates/js/foundation/foundation.dropdown.js
wireframe2html/templates/js/foundation/foundation.equalizer.js
wireframe2html/templates/js/foundation/foundation.interchange.js
