Metadata-Version: 1.1
Name: wireframe2html
Version: 0.2
Summary: Convert screen from Wireframesketcher to html 
Home-page: https://github.com/chbrun/wireframe2htm
Author: Christophe Brun
Author-email: christophe.brun.cl194@gadz.org
License: BSD
Keywords: html wireframesketcher
Platform: UNKNOWN
Classifier: Development Status :: 3 - Alpha
Classifier: Topic :: Utilities
Classifier: License :: OSI Approved :: BSD License
